<?xml version="1.0"?>
<devicetype>
	<devicetypename>
	AR511GW-1
	</devicetypename>
	<description>
	车载移动网关，上行2G/3G/4G,下行WIFI
	</description>
	<platform>
	Android5.0
	</platform>
	<serviceprotocol>
	CoAP
	</serviceprotocol>
	<managementprotocol>
	LWM2M
	</managementprotocol>
	<datastreams>
		<datastream>
			<datastreamname>
			Longitude
			</datastreamname>
			<datastreamdisplayname>
			经度
			</datastreamdisplayname>
			<datastreamtype>
			Numeric
			</datastreamtype>
			<datastreamunit>
			°
			</datastreamunit>
		</datastream>
		<datastream>
			<datastreamname>
			Latitude
			</datastreamname>
			<datastreamdisplayname>
			纬度
			</datastreamdisplayname>
			<datastreamtype>
			Numeric
			</datastreamtype>
			<datastreamunit>
			°
			</datastreamunit>
		</datastream>
		<datastream>
			<datastreamname>
			Altitude
			</datastreamname>
			<datastreamdisplayname>
			海拔
			</datastreamdisplayname>
			<datastreamtype>
			Numeric
			</datastreamtype>
			<datastreamunit>
			m
			</datastreamunit>
		</datastream>
		<datastream>
			<datastreamname>
			Speed
			</datastreamname>
			<datastreamdisplayname>
			车速
			</datastreamdisplayname>
			<datastreamtype>
			Numeric
			</datastreamtype>
			<datastreamunit>
			km/h
			</datastreamunit>
		</datastream>
	</datastreams>
</devicetype>